{"is_source_file": true, "format": "TypeScript (TSX)", "description": "This file defines an authentication context for a React application, providing user authentication state and related functions such as login, register, logout, and refresh. It manages user authentication via API calls and local storage, and offers hooks for other components to access auth state.", "external_files": ["@/lib/api"], "external_methods": ["api.post", "api.get"], "published": ["AuthContext", "useAuth", "AuthProvider"], "classes": [], "methods": [{"name": "AuthProvider", "description": "React component providing authentication context, managing user state and authentication actions."}, {"name": "useAuth", "description": "Custom hook to access authentication context."}], "calls": ["useRouter", "localStorage.getItem", "localStorage.setItem", "localStorage.removeItem", "api.get", "api.post", "router.push"], "search-terms": ["AuthContext", "AuthProvider", "useAuth", "login", "register", "logout", "refresh", "token management", "React context"], "state": 2, "file_id": 13, "knowledge_revision": 28, "git_revision": "", "ctags": [], "hash": "6216114b625b937c0c4b2c2a1cdc38b2", "format-version": 4, "code-base-name": "booking_frontend", "filename": "booking_frontend/src/lib/AuthContext.tsx", "revision_history": [{"28": ""}]}