{"is_source_file": true, "format": "TypeScript (TSX)", "description": "This file defines a React component named 'Sidebar' that is part of a Next.js application. It renders an admin sidebar with navigation links, conditionally shown based on the user's role and context.", "external_files": ["next/link", "@/lib/AuthContext", "next/navigation"], "external_methods": ["useAuth", "usePathname"], "published": ["default"], "classes": [], "methods": [{"name": "Sidebar", "description": "React functional component that renders an administrative sidebar with links, visible only to users with an 'admin' role."}], "calls": ["useAuth", "usePathname", "map"], "search-terms": ["React Sidebar", "Next.js Admin Panel", "TypeScript TSX component", "useAuth hook", "usePathname hook"], "state": 2, "file_id": 12, "knowledge_revision": 26, "git_revision": "", "ctags": [], "hash": "84d50ae352dc12485b8d03052940a261", "format-version": 4, "code-base-name": "booking_frontend", "filename": "booking_frontend/src/components/Sidebar.tsx", "revision_history": [{"26": ""}]}